chinook/ARPES_lib.py
chinook/FS_tetra.py
chinook/H_library.py
chinook/SlaterKoster.py
chinook/TB_lib.py
chinook/Tk_plot.py
chinook/Ylm.py
chinook/adaptive_int.py
chinook/angle_expt.py
chinook/atomic_mass.py
chinook/atomic_mass.txt
chinook/build_lib.py
chinook/dos.py
chinook/electron_configs.py
chinook/electron_configs.txt
chinook/intensity_map.py
chinook/klib.py
chinook/lattice_lib.py
chinook/matplotlib_plotter.py
chinook/operator_library.py
chinook/orbital.py
chinook/orbital_plotting.py
chinook/radint_lib.py
chinook/rotation_lib.py
chinook/slab.py
chinook/surface_vector.py
chinook/tetrahedra.py
chinook/tilt.py
chinook/v3find.py
chinook/wigner.py
chinook-1.1.3.dist-info/LICENSE
chinook-1.1.3.dist-info/METADATA
chinook-1.1.3.dist-info/WHEEL
chinook-1.1.3.dist-info/top_level.txt
chinook-1.1.3.dist-info/RECORD
