Metadata-Version: 2.1
Name: chinook
Version: 1.1.3
Summary: Tools for tight-binding and simulation of ARPES
Home-page: https://github.com/rpday/chinook
Author: Ryan P. Day
Author-email: ryanday7@gmail.com
License: MIT
Platform: UNKNOWN
Classifier: Development Status :: 4 - Beta
Classifier: License :: OSI Approved :: MIT License
Classifier: Programming Language :: Python :: 3 :: Only
Classifier: Topic :: Scientific/Engineering :: Physics
Classifier: Operating System :: OS Independent
License-File: LICENSE
Requires-Dist: numpy
Requires-Dist: matplotlib
Requires-Dist: scipy
